propp_fr/__init__.py
propp_fr/propp_fr_add_entities_features.py
propp_fr/propp_fr_coreference_resolution_module.py
propp_fr/propp_fr_extract_attributes.py
propp_fr/propp_fr_gender.py
propp_fr/propp_fr_generate_character_network.py
propp_fr/propp_fr_generate_characters_dict.py
propp_fr/propp_fr_generate_sacr_file.py
propp_fr/propp_fr_generate_tokens_and_entities_from_sacr.py
propp_fr/propp_fr_generate_tokens_df.py
propp_fr/propp_fr_generate_tokens_embeddings_tensor.py
propp_fr/propp_fr_load_save_functions.py
propp_fr/propp_fr_mentions_detection_module.py
propp_fr/propp_fr_number.py
propp_fr/propp_fr_single_line_command.py
propp_fr/data/insee_names_fr_1900_2023.csv
propp_fr-0.0.91.dist-info/METADATA
propp_fr-0.0.91.dist-info/WHEEL
propp_fr-0.0.91.dist-info/top_level.txt
propp_fr-0.0.91.dist-info/RECORD
